qocogen/__init__.py
qocogen/codegen.py
qocogen/codegen_utils.py
qocogen/interface.py
qocogen-0.1.9.dist-info/METADATA
qocogen-0.1.9.dist-info/WHEEL
qocogen-0.1.9.dist-info/licenses/LICENSE
qocogen-0.1.9.dist-info/RECORD
